{
  "football": [
      {
    "time": "2024-12-05T17:00:00",
    "teams": "Persepolis (Iran) vs Al Shorta (Iraq)",
    "competition": "AFC Champions League",
    "stream": "https://12a001a90a8c45927f7710a6ee02e8e6.v.smtcdns.net/play1nm.hnyongshun.cn/live/ballbar_9430.m3u8",
    "isLive": false
  },
  {
    "time": "2024-12-03T03:00:00",
    "teams": "Sevilla vs Osasuna",
    "competition": "La Liga",
    "stream": "https://12a001a90a8c45927f7710a6ee02e8e6.v.smtcdns.net/play1nm.hnyongshun.cn/live/ballbar_20610.m3u8",
    "isLive": false
  }
  ],
  "motogp": [
    {
      "time": "2024-12-01T14:00:00",
      "teams": "MotoGP Race 1",
      "competition": "MotoGP Championship",
      "stream": "https://example.com/motogp-live-stream.m3u8",
      "isLive": false
    }
  ],
  "f1": [
  {
    "time": "2024-12-05T17:00:00",
    "teams": "Grand Prix",
    "competition": "Formula 1 - Grand Prix Abu Dhabi",
    "stream": "https://12a001a90a8c45927f7710a6ee02e8e6.v.smtcdns.net/play1nm.hnyongshun.cn/live/ballbar_36060.m3u8",
    "isLive": false
  }
  ],
  "badminton": [
    {
    "time": "2024-12-05T17:00:00",
      "teams": "COURT 1",
      "competition": "Badminton - YONEX-SUNRISE Guwahati Masters 2024",
      "stream": "https://12a001a90a8c45927f7710a6ee02e8e6.v.smtcdns.net/play1nm.hnyongshun.cn/live/ballbar_29120.m3u8",
      "isLive": false
    },
    {
    "time": "2024-12-05T17:00:00",
      "teams": "COURT 2",
      "competition": "Badminton - YONEX-SUNRISE Guwahati Masters 2024",
      "stream": "https://12a001a90a8c45927f7710a6ee02e8e6.v.smtcdns.net/play1nm.hnyongshun.cn/live/ballbar_30380.m3u8",
      "isLive": false
    },
    {
    "time": "2024-12-05T17:00:00",
      "teams": "COURT 3",
      "competition": "Badminton - YONEX-SUNRISE Guwahati Masters 2024",
      "stream": "https://12a001a90a8c45927f7710a6ee02e8e6.v.smtcdns.net/play1nm.hnyongshun.cn/live/ballbar_27410.m3u8",
      "isLive": false
    },
    {
    "time": "2024-12-05T17:00:00",
      "teams": "COURT 4",
      "competition": "Badminton - YONEX-SUNRISE Guwahati Masters 2024",
      "stream": "https://12a001a90a8c45927f7710a6ee02e8e6.v.smtcdns.net/play1nm.hnyongshun.cn/live/ballbar_29920.m3u8",
      "isLive": false
    },
    {
    "time": "2024-12-05T17:00:00",
      "teams": "COURT 5",
      "competition": "Badminton - YONEX-SUNRISE Guwahati Masters 2024",
      "stream": "https://12a001a90a8c45927f7710a6ee02e8e6.v.smtcdns.net/play1nm.hnyongshun.cn/live/ballbar_27580.m3u8",
      "isLive": false
    }
  ],
  "basketball": [
  {
    "time": "2024-12-05T17:00:00",
    "teams": "Minnesota Timberwolves vs Los Angeles Lakers",
    "competition": "NBA",
    "stream": "https://12a001a90a8c45927f7710a6ee02e8e6.v.smtcdns.net/play1nm.hnyongshun.cn/live/ballbar_33820.m3u8",
    "isLive": false
  }
  ]
}
